mov_cli_soundcloud/__init__.py
mov_cli_soundcloud/scraper.py
mov_cli_soundcloud-1.0.1.dist-info/LICENSE
mov_cli_soundcloud-1.0.1.dist-info/METADATA
mov_cli_soundcloud-1.0.1.dist-info/WHEEL
mov_cli_soundcloud-1.0.1.dist-info/top_level.txt
mov_cli_soundcloud-1.0.1.dist-info/RECORD
