Metadata-Version: 2.1
Name: mov-cli-soundcloud
Version: 1.0.1
Summary: A mov-cli plugin for playing soundcloud.
Author-email: r3tr0ananas <ananas@ananas.moe>
License: MIT License
Project-URL: GitHub, https://github.com/mov-cli/mov-cli-soundcloud
Project-URL: BugTracker, https://github.com/mov-cli/mov-cli-soundcloud/issues
Keywords: amazing mov-cli plugin
Classifier: Operating System :: Microsoft :: Windows :: Windows 11
Classifier: Operating System :: Microsoft :: Windows :: Windows 10
Classifier: Operating System :: POSIX :: Linux
Classifier: License :: OSI Approved :: MIT License
Classifier: Programming Language :: Python :: 3.8
Classifier: Programming Language :: Python :: 3.9
Classifier: Programming Language :: Python :: 3.10
Classifier: Programming Language :: Python :: 3.11
Classifier: Programming Language :: Python :: 3.12
Requires-Python: >=3.8
License-File: LICENSE
Requires-Dist: requests
Requires-Dist: importlib-metadata ; python_version < "3.8"
Provides-Extra: dev
Requires-Dist: ruff ; extra == 'dev'
Requires-Dist: build ; extra == 'dev'
